{
  "minecraft:recipes/decorations/ladder": {
    "criteria": {
      "has_stick": "2026-06-14 02:34:12 +0900"
    },
    "done": true
  },
  "minecraft:recipes/food/baked_potato_from_campfire_cooking": {
    "criteria": {
      "has_potato": "2026-06-14 02:34:53 +0900"
    },
    "done": true
  },
  "minecraft:recipes/food/baked_potato": {
    "criteria": {
      "has_potato": "2026-06-14 02:34:53 +0900"
    },
    "done": true
  },
  "minecraft:recipes/decorations/soul_lantern": {
    "criteria": {
      "has_soul_torch": "2026-06-14 02:30:13 +0900"
    },
    "done": true
  },
  "minecraft:recipes/tools/wooden_axe": {
    "criteria": {
      "has_stick": "2026-06-14 02:34:12 +0900"
    },
    "done": true
  },
  "minecraft:recipes/combat/wooden_spear": {
    "criteria": {
      "has_stick": "2026-06-14 02:34:12 +0900"
    },
    "done": true
  },
  "minecraft:recipes/decorations/crafting_table": {
    "criteria": {
      "unlock_right_away": "2026-06-14 02:29:28 +0900"
    },
    "done": true
  },
  "minecraft:recipes/transportation/cherry_boat": {
    "criteria": {
      "in_water": "2026-06-14 02:32:26 +0900"
    },
    "done": true
  },
  "minecraft:recipes/transportation/bamboo_raft": {
    "criteria": {
      "in_water": "2026-06-14 02:32:26 +0900"
    },
    "done": true
  },
  "minecraft:recipes/food/bread": {
    "criteria": {
      "has_wheat": "2026-06-14 02:34:53 +0900"
    },
    "done": true
  },
  "minecraft:recipes/transportation/spruce_boat": {
    "criteria": {
      "in_water": "2026-06-14 02:32:26 +0900"
    },
    "done": true
  },
  "minecraft:recipes/building_blocks/hay_block": {
    "criteria": {
      "has_wheat": "2026-06-14 02:34:53 +0900"
    },
    "done": true
  },
  "minecraft:recipes/transportation/birch_boat": {
    "criteria": {
      "in_water": "2026-06-14 02:32:26 +0900"
    },
    "done": true
  },
  "minecraft:recipes/transportation/oak_boat": {
    "criteria": {
      "in_water": "2026-06-14 02:32:26 +0900"
    },
    "done": true
  },
  "minecraft:recipes/transportation/mangrove_boat": {
    "criteria": {
      "in_water": "2026-06-14 02:32:26 +0900"
    },
    "done": true
  },
  "minecraft:recipes/decorations/campfire": {
    "criteria": {
      "has_stick": "2026-06-14 02:34:12 +0900"
    },
    "done": true
  },
  "minecraft:recipes/tools/wooden_hoe": {
    "criteria": {
      "has_stick": "2026-06-14 02:34:12 +0900"
    },
    "done": true
  },
  "minecraft:recipes/tools/wooden_pickaxe": {
    "criteria": {
      "has_stick": "2026-06-14 02:34:12 +0900"
    },
    "done": true
  },
  "minecraft:recipes/food/baked_potato_from_smoking": {
    "criteria": {
      "has_potato": "2026-06-14 02:34:53 +0900"
    },
    "done": true
  },
  "minecraft:recipes/transportation/carrot_on_a_stick": {
    "criteria": {
      "has_carrot": "2026-06-14 02:32:30 +0900"
    },
    "done": true
  },
  "minecraft:recipes/tools/wooden_shovel": {
    "criteria": {
      "has_stick": "2026-06-14 02:34:12 +0900"
    },
    "done": true
  },
  "minecraft:recipes/transportation/acacia_boat": {
    "criteria": {
      "in_water": "2026-06-14 02:32:26 +0900"
    },
    "done": true
  },
  "minecraft:recipes/combat/wooden_sword": {
    "criteria": {
      "has_stick": "2026-06-14 02:34:12 +0900"
    },
    "done": true
  },
  "minecraft:recipes/transportation/pale_oak_boat": {
    "criteria": {
      "in_water": "2026-06-14 02:32:26 +0900"
    },
    "done": true
  },
  "minecraft:recipes/transportation/jungle_boat": {
    "criteria": {
      "in_water": "2026-06-14 02:32:26 +0900"
    },
    "done": true
  },
  "minecraft:recipes/transportation/dark_oak_boat": {
    "criteria": {
      "in_water": "2026-06-14 02:32:26 +0900"
    },
    "done": true
  },
  "DataVersion": 4790
}